foxTemplateEngine/__init__.py
foxTemplateEngine/template_engine.py
tests/__init__.py
tests/test_transform.py
foxTemplateEngine-2.1.1.dist-info/LICENSE
foxTemplateEngine-2.1.1.dist-info/METADATA
foxTemplateEngine-2.1.1.dist-info/WHEEL
foxTemplateEngine-2.1.1.dist-info/top_level.txt
foxTemplateEngine-2.1.1.dist-info/RECORD
