Metadata-Version: 2.1
Name: foxTemplateEngine
Version: 2.1.1
Summary: Template Engine for HTML
Home-page: https://github.com/leroykiddd/templateEngine
Author: Petrov D.A.
Author-email: leroykid02@mail.ru
License: UNKNOWN
Platform: any
Requires-Python: >=3.7
